jupyter_server_documents/__init__.py
jupyter_server_documents/_version.py
jupyter_server_documents/app.py
jupyter_server_documents/handlers.py
jupyter_server_documents/session_manager.py
jupyter_server_documents/ydocs.py
jupyter_server_documents/events/__init__.py
jupyter_server_documents/events/awareness.yaml
jupyter_server_documents/events/room.yaml
jupyter_server_documents/jcollab_api/__init__.py
jupyter_server_documents/jcollab_api/jcollab_api.py
jupyter_server_documents/kernels/__init__.py
jupyter_server_documents/kernels/kernel_client.py
jupyter_server_documents/kernels/kernel_client_abc.py
jupyter_server_documents/kernels/kernel_manager.py
jupyter_server_documents/kernels/message_cache.py
jupyter_server_documents/kernels/multi_kernel_manager.py
jupyter_server_documents/kernels/states.py
jupyter_server_documents/kernels/websocket_connection.py
jupyter_server_documents/outputs/__init__.py
jupyter_server_documents/outputs/handlers.py
jupyter_server_documents/outputs/manager.py
jupyter_server_documents/outputs/optimized_outputs_manager.py
jupyter_server_documents/outputs/output_processor.py
jupyter_server_documents/rooms/__init__.py
jupyter_server_documents/rooms/mock_yroom.py
jupyter_server_documents/rooms/yroom.py
jupyter_server_documents/rooms/yroom_events_api.py
jupyter_server_documents/rooms/yroom_file_api.py
jupyter_server_documents/rooms/yroom_manager.py
jupyter_server_documents/tests/__init__.py
jupyter_server_documents/tests/test_kernel_message_cache.py
jupyter_server_documents/tests/test_output_processor.py
jupyter_server_documents/tests/test_outputs_manager.py
jupyter_server_documents/tests/test_yroom.py
jupyter_server_documents/tests/test_yroom_file_api.py
jupyter_server_documents/tests/kernels/__init__.py
jupyter_server_documents/tests/kernels/conftest.py
jupyter_server_documents/tests/kernels/test_kernel_client.py
jupyter_server_documents/tests/kernels/test_kernel_client_integration.py
jupyter_server_documents/tests/kernels/test_kernel_manager.py
jupyter_server_documents-0.1.0a8.dist-info/METADATA
jupyter_server_documents-0.1.0a8.dist-info/WHEEL
jupyter_server_documents-0.1.0a8.dist-info/licenses/LICENSE
jupyter_server_documents-0.1.0a8.dist-info/RECORD
